tbd_api-0.0.6.dist-info/licenses/LICENSE
torrentbd_api/__init__.py
torrentbd_api/active.py
torrentbd_api/api.py
torrentbd_api/login.py
torrentbd_api/main.py
torrentbd_api/profile.py
torrentbd_api/schema.py
torrentbd_api/search.py
torrentbd_api/version.py
torrentbd_api/static/index.html
torrentbd_api/static/css/styles.css
torrentbd_api/static/js/script.js
tbd_api-0.0.6.dist-info/METADATA
tbd_api-0.0.6.dist-info/WHEEL
tbd_api-0.0.6.dist-info/entry_points.txt
tbd_api-0.0.6.dist-info/top_level.txt
tbd_api-0.0.6.dist-info/RECORD
