Metadata-Version: 2.4
Name: tbd-api
Version: 0.0.6
Summary: Unofficial API for TorrentBD
Author-email: TanmoyTheBoT <tanmoysarkershuvo@gmail.com>
License: MIT
Project-URL: Homepage, https://github.com/TanmoyTheBoT/torrentbd-api
Classifier: Programming Language :: Python :: 3
Classifier: License :: OSI Approved :: MIT License
Classifier: Operating System :: OS Independent
Requires-Python: >=3.12
License-File: LICENSE
Requires-Dist: python-dotenv>=0.9.9
Requires-Dist: fastapi>=0.115.12
Requires-Dist: pyotp>=2.9.0
Requires-Dist: requests>=2.32.3
Requires-Dist: uvicorn>=0.34.2
Requires-Dist: v3cap>=0.0.2
Requires-Dist: beautifulsoup4>=4.13.4
Requires-Dist: brotli>=1.1.0
Provides-Extra: dev
Requires-Dist: bandit>=1.8.3; extra == "dev"
Requires-Dist: black>=25.1.0; extra == "dev"
Requires-Dist: build>=1.2.2.post1; extra == "dev"
Requires-Dist: flake8>=7.2.0; extra == "dev"
Requires-Dist: isort>=6.0.1; extra == "dev"
Requires-Dist: mypy>=1.15.0; extra == "dev"
Requires-Dist: ruff>=0.11.8; extra == "dev"
Requires-Dist: twine>=6.1.0; extra == "dev"
Requires-Dist: types-beautifulsoup4>=4.12.0.20250204; extra == "dev"
Requires-Dist: types-requests>=2.32.0.20250328; extra == "dev"
Requires-Dist: pre-commit>=4.2.0; extra == "dev"
Dynamic: license-file
